{
    "relation": 15,
    "describe": 14,
    "interface": 12,
    "virtual": 12,
    "world": 12,
    "present": 10,
    "summary": 10,
    "user": 10,
    "ulysse": 10,
    "structural": 9,
    "new": 8,
    "kind": 8,
    "interaction": 8,
    "design": 8,
    "web": 8,
    "noise": 8,
    "string": 8,
    "test": 7,
    "set": 7,
    "disambiguation": 6,
    "lexical": 6,
    "dependency": 6,
    "modality": 6,
    "given": 6,
    "language": 6,
    "distribution": 6,
    "frame": 6,
    "microprocessor": 6,
    "hash": 6,
    "valid": 6,
    "collision": 6,
    "summarizer": 5,
    "called": 5,
    "mead": 5,
    "generates": 5,
    "cluster": 5,
    "centroid": 5,
    "produced": 5,
    "detection": 5,
    "tracking": 5,
    "sentence": 5,
    "utility": 5,
    "subsumption": 5,
    "evaluation": 5,
    "single": 5,
    "multiple": 5,
    "finally": 5,
    "summarization": 5,
    "paper": 5,
    "proposes": 5,
    "additive": 5,
    "sound": 5,
    "experiment": 4,
    "keyboard": 4,
    "difficult": 4,
    "usable": 4,
    "input": 4,
    "much": 4,
    "therefore": 4,
    "usability": 4,
    "agent": 4,
    "help": 4,
    "motion": 4,
    "order": 4,
    "well": 4,
    "skeleton": 4,
    "wide": 4,
    "estimating": 4,
    "word": 4,
    "number": 4,
    "english": 4,
    "cepstral": 4,
    "cepstrum": 4,
    "coefficient": 4,
    "fast": 4,
    "small": 4,
    "microcontroller": 4,
    "command": 4,
    "narrow": 4,
    "function": 4,
    "explores": 3,
    "important": 3,
    "syntactic": 3,
    "widely": 3,
    "complementary": 3,
    "capability": 3,
    "report": 3,
    "showing": 3,
    "benefit": 3,
    "enrichment": 3,
    "environment": 3,
    "project": 3,
    "becoming": 2,
    "increasingly": 2,
    "popular": 2,
    "especially": 2,
    "situation": 2,
    "mouse": 2,
    "however": 2,
    "despite": 2,
    "fact": 2,
    "many": 2,
    "hailed": 2,
    "inherently": 2,
    "since": 2,
    "everyone": 2,
    "already": 2,
    "know": 2,
    "talk": 2,
    "left": 2,
    "feeling": 2,
    "disappointed": 2,
    "quality": 2,
    "clearly": 2,
    "work": 2,
    "done": 2,
    "spoken": 2,
    "believe": 2,
    "major": 2,
    "problem": 2,
    "namely": 2,
    "people": 2,
    "currently": 2,
    "working": 2,
    "part": 2,
    "designer": 2,
    "experience": 2,
    "issue": 2,
    "chi": 2,
    "community": 2,
    "vastly": 2,
    "property": 2,
    "requires": 2,
    "measure": 2,
    "first": 2,
    "discus": 2,
    "respective": 2,
    "advantage": 2,
    "image": 2,
    "example": 2,
    "verbal": 2,
    "reality": 2,
    "conversational": 2,
    "navigate": 2,
    "designed": 2,
    "embedded": 2,
    "participant": 2,
    "conference": 2,
    "responds": 2,
    "positively": 2,
    "navigates": 2,
    "viewpoint": 2,
    "behalf": 2,
    "carried": 2,
    "discovered": 2,
    "novice": 2,
    "experienced": 2,
    "difficulty": 2,
    "moving": 2,
    "carry": 2,
    "navigation": 2,
    "impossible": 2,
    "classical": 2,
    "device": 2,
    "whole": 2,
    "stripped": 2,
    "architecture": 2,
    "ported": 2,
    "vrml": 2,
    "java": 2,
    "prolog": 2,
    "hope": 2,
    "application": 2,
    "grown": 2,
    "big": 2,
    "anarchic": 2,
    "fashion": 2,
    "evident": 2,
    "intrinsic": 2,
    "characteristic": 2,
    "multilinguality": 2,
    "size": 2,
    "frequency": 2,
    "commonly": 2,
    "occurring": 2,
    "available": 2,
    "browser": 2,
    "calculate": 2,
    "growth": 2,
    "european": 2,
    "expected": 2,
    "growing": 2,
    "faster": 2,
    "pace": 2,
    "though": 2,
    "position": 2,
    "still": 2,
    "dominant": 2,
    "effect": 2,
    "white": 2,
    "signal": 2,
    "individual": 2,
    "shown": 2,
    "depend": 2,
    "strongly": 2,
    "overlap": 2,
    "suggest": 2,
    "scalar": 2,
    "quantity": 2,
    "equal": 2,
    "sum": 2,
    "weighted": 2,
    "able": 2,
    "classify": 2,
    "containing": 2,
    "reasonably": 2,
    "separated": 2,
    "snr": 2,
    "db": 2,
    "demonstrating": 2,
    "feasibility": 2,
    "robust": 2,
    "detector": 2,
    "identification": 2,
    "fixed": 2,
    "terminal": 2,
    "memory": 2,
    "requirement": 2,
    "traditional": 2,
    "full": 2,
    "storage": 2,
    "feed": 2,
    "character": 2,
    "via": 2,
    "another": 2,
    "sends": 2,
    "identify": 2,
    "ensuring": 2,
    "hashed": 2,
    "criterion": 2,
    "random": 2,
    "proposed": 2,
    "possibility": 2,
    "latter": 2,
    "achieving": 2,
    "code": 2,
    "execution": 2,
    "hashing": 2,
    "achieved": 2,
    "rotating": 2,
    "iterative": 2,
    "form": 2,
    "easily": 2,
    "simple": 2,
    "microcontrollers": 2,
    "presented": 2,
    "according": 2,
    "efficiency": 2,
    "program": 2,
    "appendix": 2,
    "article": 2,
    "describes": 2,
    "computer": 2,
    "scientific": 2,
    "digital": 2,
    "synthesis": 2,
    "visualization": 2,
    "collaborative": 1,
    "researcher": 1,
    "mathematics": 1,
    "science": 1,
    "division": 1,
    "argonne": 1,
    "national": 1,
    "laboratory": 1,
    "music": 1,
    "university": 1,
    "illinois": 1,
    "focus": 1,
    "exploration": 1,
    "analysis": 1,
    "complex": 1,
    "computing": 1,
    "address": 1,
    "context": 1,
    "dias": 1,
    "instrument": 1,
    "mean": 1,
    "procedure": 1,
    "preliminary": 1,
    "sonification": 1
}