{
    "host": 22,
    "agent": 18,
    "protocol": 16,
    "mobile": 12,
    "key": 8,
    "multipoint": 7,
    "code": 6,
    "remote": 6,
    "protected": 6,
    "collected": 6,
    "state": 6,
    "support": 5,
    "rule": 5,
    "paper": 5,
    "multicast": 5,
    "integrity": 4,
    "required": 4,
    "untrusted": 4,
    "case": 4,
    "rely": 4,
    "carrying": 4,
    "must": 4,
    "removing": 4,
    "sent": 4,
    "scheme": 4,
    "allows": 4,
    "change": 4,
    "time": 4,
    "handling": 4,
    "new": 4,
    "space": 4,
    "scenario": 4,
    "generation": 4,
    "problem": 4,
    "search": 4,
    "way": 3,
    "work": 3,
    "distributed": 3,
    "first": 3,
    "packet": 3,
    "routing": 3,
    "address": 3,
    "application": 3,
    "synthesis": 3,
    "test": 3,
    "delay": 3,
    "lan": 3,
    "topology": 3,
    "forward": 3,
    "pad": 2,
    "otp": 2,
    "cipher": 2,
    "insure": 2,
    "arrives": 2,
    "presented": 2,
    "retrieve": 2,
    "confidential": 2,
    "encrypted": 2,
    "node": 2,
    "prerequisite": 2,
    "counterfeiting": 2,
    "cover": 2,
    "described": 2,
    "article": 2,
    "seems": 2,
    "simple": 2,
    "enough": 2,
    "easily": 2,
    "protecting": 2,
    "requires": 2,
    "development": 2,
    "allow": 2,
    "digital": 2,
    "signature": 2,
    "stolen": 2,
    "counterfeit": 2,
    "hostile": 2,
    "consequence": 2,
    "authorized": 2,
    "modify": 2,
    "changing": 2,
    "retrieved": 2,
    "proposed": 2,
    "done": 2,
    "standard": 2,
    "cryptography": 2,
    "modified": 2,
    "environment": 2,
    "without": 2,
    "requiring": 2,
    "interactive": 2,
    "dropped": 2,
    "stand": 2,
    "fact": 2,
    "allowing": 2,
    "return": 2,
    "originating": 2,
    "set": 2,
    "internet": 2,
    "range": 2,
    "source": 2,
    "destination": 2,
    "priority": 2,
    "action": 2,
    "complexity": 2,
    "present": 2,
    "automatic": 2,
    "searching": 2,
    "synthesize": 2,
    "finite": 2,
    "fsm": 2,
    "extend": 2,
    "criterion": 2,
    "virtual": 2,
    "underlying": 2,
    "distribution": 2,
    "tree": 2,
    "response": 2,
    "systematic": 2,
    "sequence": 2,
    "event": 2,
    "correctness": 2,
    "explosion": 2,
    "backward": 2,
    "reduced": 2,
    "however": 2,
    "growing": 2,
    "interest": 2,
    "part": 2,
    "component": 2,
    "high": 2,
    "white": 2,
    "put": 2,
    "together": 2,
    "consider": 1,
    "filtering": 1,
    "consists": 1,
    "given": 1,
    "handled": 1,
    "maximum": 1,
    "match": 1,
    "describe": 1,
    "structure": 1,
    "quickly": 1,
    "matching": 1,
    "incoming": 1,
    "determining": 1,
    "whether": 1,
    "contains": 1,
    "conflict": 1,
    "advent": 1,
    "growth": 1,
    "complicated": 1,
    "worst": 1,
    "best": 1,
    "fotg": 1,
    "global": 1,
    "timing": 1,
    "semantics": 1,
    "handle": 1,
    "introduce": 1,
    "notion": 1,
    "represent": 1,
    "variant": 1,
    "timer": 1,
    "suppression": 1,
    "mechanism": 1,
    "various": 1,
    "respect": 1,
    "overhead": 1,
    "message": 1,
    "simulation": 1,
    "reliable": 1,
    "show": 1,
    "scalable": 1,
    "synthesizing": 1,
    "automatically": 1,
    "expect": 1,
    "serve": 1,
    "methodology": 1,
    "attempt": 1,
    "stress": 1,
    "viewed": 1,
    "suffers": 1,
    "goal": 1,
    "circumvent": 1,
    "knowledge": 1,
    "fault": 1,
    "investigated": 1,
    "extended": 1,
    "reachability": 1,
    "exponential": 1,
    "polynomial": 1,
    "number": 1,
    "router": 1,
    "fully": 1,
    "automate": 1,
    "second": 1,
    "backtracking": 1,
    "generate": 1,
    "instead": 1,
    "initial": 1,
    "pim": 1,
    "propose": 1,
    "represents": 1,
    "cluster": 1,
    "evident": 1,
    "area": 1,
    "traditionally": 1,
    "parallel": 1,
    "platform": 1,
    "fuelled": 1,
    "powerful": 1,
    "microprocessor": 1,
    "network": 1,
    "commodity": 1,
    "well": 1,
    "rapidly": 1,
    "maturing": 1,
    "software": 1,
    "available": 1,
    "broken": 1,
    "section": 1,
    "academic": 1,
    "industrial": 1,
    "researcher": 1,
    "expert": 1,
    "field": 1,
    "willing": 1,
    "volunteer": 1,
    "effort": 1,
    "status": 1,
    "draft": 1,
    "stage": 1,
    "publicizing": 1,
    "presence": 1,
    "request": 1,
    "comment": 1,
    "rfc": 1
}