{
    "problem": 40,
    "mesh": 33,
    "memory": 31,
    "set": 21,
    "solution": 21,
    "layout": 21,
    "optimal": 19,
    "paper": 18,
    "show": 17,
    "local": 16,
    "work": 16,
    "sparse": 15,
    "update": 15,
    "number": 14,
    "parameter": 14,
    "value": 14,
    "real": 14,
    "proof": 14,
    "high": 14,
    "task": 14,
    "application": 13,
    "many": 13,
    "operation": 13,
    "initialization": 12,
    "stage": 12,
    "tree": 12,
    "several": 11,
    "linear": 10,
    "calculation": 10,
    "interval": 10,
    "order": 10,
    "computation": 10,
    "present": 10,
    "factor": 9,
    "obtain": 9,
    "well": 9,
    "bound": 9,
    "numerical": 9,
    "size": 9,
    "transfer": 9,
    "expectation": 9,
    "obtained": 9,
    "global": 8,
    "particular": 8,
    "test": 8,
    "function": 8,
    "formally": 8,
    "arithmetic": 8,
    "give": 8,
    "precision": 8,
    "transform": 8,
    "input": 8,
    "case": 8,
    "decomposition": 8,
    "shell": 8,
    "opa": 8,
    "adjoint": 8,
    "code": 8,
    "blopex": 8,
    "variable": 7,
    "domain": 7,
    "user": 7,
    "required": 7,
    "given": 7,
    "recently": 7,
    "first": 7,
    "may": 7,
    "automatic": 7,
    "multiplication": 7,
    "block": 7,
    "run": 7,
    "schedule": 7,
    "solver": 7,
    "gappa": 7,
    "achieve": 6,
    "advantage": 6,
    "property": 6,
    "polyhedron": 6,
    "important": 6,
    "count": 6,
    "improved": 6,
    "called": 6,
    "vertex": 6,
    "cache": 6,
    "fully": 6,
    "traversal": 6,
    "leaf": 6,
    "project": 6,
    "tool": 6,
    "new": 6,
    "execution": 6,
    "combination": 5,
    "limited": 5,
    "reduced": 5,
    "et": 5,
    "al": 5,
    "depend": 5,
    "methodology": 5,
    "propose": 5,
    "solving": 5,
    "reduces": 5,
    "various": 5,
    "interest": 5,
    "proposed": 5,
    "basis": 5,
    "analysis": 5,
    "range": 5,
    "asymptotically": 5,
    "recursive": 5,
    "form": 5,
    "among": 5,
    "general": 5,
    "small": 5,
    "software": 5,
    "package": 5,
    "available": 5,
    "petsc": 5,
    "equation": 5,
    "preconditioners": 5,
    "matrix": 5,
    "amount": 4,
    "coefficient": 4,
    "term": 4,
    "brief": 4,
    "arise": 4,
    "deal": 4,
    "nonlinearity": 4,
    "quite": 4,
    "demand": 4,
    "rather": 4,
    "inherent": 4,
    "hence": 4,
    "inherited": 4,
    "literature": 4,
    "popularly": 4,
    "known": 4,
    "ideal": 4,
    "transformation": 4,
    "equilibrium": 4,
    "characterization": 4,
    "systematically": 4,
    "explores": 4,
    "subspace": 4,
    "complete": 4,
    "thesis": 4,
    "namely": 4,
    "repeated": 4,
    "alternatively": 4,
    "improvement": 4,
    "tested": 4,
    "synthetic": 4,
    "novel": 4,
    "clearly": 4,
    "manifested": 4,
    "sensitivity": 4,
    "allows": 4,
    "flexibility": 4,
    "practitioner": 4,
    "hierarchical": 4,
    "like": 4,
    "evolutionary": 4,
    "smoothing": 4,
    "framework": 4,
    "combining": 4,
    "elementary": 4,
    "prover": 4,
    "lower": 4,
    "dependency": 4,
    "verified": 4,
    "development": 4,
    "strategy": 4,
    "abstraction": 4,
    "polyhedral": 4,
    "area": 4,
    "possible": 4,
    "improve": 4,
    "discrete": 4,
    "dct": 4,
    "accuracy": 4,
    "certain": 4,
    "rescaling": 4,
    "second": 4,
    "almost": 4,
    "option": 4,
    "containing": 4,
    "sample": 4,
    "probability": 4,
    "distribution": 4,
    "cost": 4,
    "risk": 4,
    "major": 4,
    "written": 4,
    "time": 4,
    "rounded": 4,
    "operator": 4,
    "environment": 4,
    "computer": 4,
    "hypre": 4,
    "computational": 4,
    "parallelism": 4,
    "factorization": 4,
    "seek": 3,
    "explaining": 3,
    "maximum": 3,
    "nonzero": 3,
    "simple": 3,
    "allow": 3,
    "interpret": 3,
    "cluster": 3,
    "begin": 3,
    "introduction": 3,
    "motivation": 3,
    "detail": 3,
    "classic": 3,
    "arising": 3,
    "biology": 3,
    "handle": 3,
    "establish": 3,
    "reduce": 3,
    "includes": 3,
    "type": 3,
    "addition": 3,
    "output": 3,
    "recent": 3,
    "fast": 3,
    "graph": 3,
    "divide": 3,
    "physical": 3,
    "space": 3,
    "region": 3,
    "collision": 3,
    "primitive": 3,
    "store": 3,
    "repeatedly": 3,
    "stored": 3,
    "neighboring": 3,
    "depends": 3,
    "guarantee": 3,
    "degrades": 3,
    "smaller": 3,
    "ram": 3,
    "dam": 3,
    "balanced": 3,
    "faster": 3,
    "multiple": 3,
    "rewriting": 3,
    "expression": 3,
    "higher": 3,
    "coq": 3,
    "square": 3,
    "becomes": 3,
    "complexity": 3,
    "libopt": 3,
    "collection": 3,
    "world": 3,
    "example": 3,
    "possibility": 3,
    "representation": 3,
    "presence": 3,
    "standard": 3,
    "program": 3,
    "eigenvalue": 3,
    "differential": 3,
    "module": 3,
    "double": 3,
    "processor": 3,
    "requirement": 3,
    "level": 3,
    "constant": 3,
    "sum": 3,
    "ldp": 3,
    "argument": 3,
    "reduction": 3,
    "accurate": 3,
    "remarkably": 2,
    "difficult": 2,
    "mechanical": 2,
    "within": 2,
    "assistant": 2,
    "convenient": 2,
    "automated": 2,
    "interactive": 2,
    "way": 2,
    "upper": 2,
    "rational": 2,
    "place": 2,
    "algebraic": 2,
    "setting": 2,
    "effect": 2,
    "integrate": 2,
    "splitting": 2,
    "taylor": 2,
    "series": 2,
    "expansion": 2,
    "pragmatic": 2,
    "customizable": 2,
    "automate": 2,
    "involving": 2,
    "explicit": 2,
    "ultimate": 2,
    "goal": 2,
    "guaranteed": 2,
    "minimal": 2,
    "human": 2,
    "interaction": 2,
    "convex": 2,
    "static": 2,
    "verification": 2,
    "complex": 2,
    "mission": 2,
    "critical": 2,
    "identification": 2,
    "appropriate": 2,
    "particularly": 2,
    "acute": 2,
    "availability": 2,
    "wide": 2,
    "spectrum": 2,
    "alternative": 2,
    "mandatory": 2,
    "survey": 2,
    "overview": 2,
    "class": 2,
    "adopted": 2,
    "outline": 2,
    "main": 2,
    "analyzer": 2,
    "verifier": 2,
    "look": 2,
    "potential": 2,
    "theoretical": 2,
    "investigation": 2,
    "contribution": 2,
    "highlighted": 2,
    "cosine": 2,
    "sine": 2,
    "dst": 2,
    "ii": 2,
    "iii": 2,
    "previously": 2,
    "published": 2,
    "without": 2,
    "sacrificing": 2,
    "furthermore": 2,
    "saved": 2,
    "generalizing": 2,
    "arai": 2,
    "derived": 2,
    "considering": 2,
    "special": 2,
    "dft": 2,
    "length": 2,
    "symmetry": 2,
    "pruning": 2,
    "redundant": 2,
    "fourier": 2,
    "split": 2,
    "radix": 2,
    "follow": 2,
    "immediately": 2,
    "rops": 2,
    "outer": 2,
    "simulated": 2,
    "annealing": 2,
    "asa": 2,
    "optimizes": 2,
    "strategic": 2,
    "plan": 2,
    "ordered": 2,
    "middle": 2,
    "duration": 2,
    "inner": 2,
    "pathtree": 2,
    "trading": 2,
    "dimension": 2,
    "trd": 2,
    "relative": 2,
    "ocean": 2,
    "circulation": 2,
    "lodyc": 2,
    "team": 2,
    "paris": 2,
    "vi": 2,
    "university": 2,
    "undergone": 2,
    "migrating": 2,
    "need": 2,
    "rebuilt": 2,
    "earlier": 2,
    "version": 2,
    "hand": 2,
    "differentiation": 2,
    "tapenade": 2,
    "build": 2,
    "mechanicaly": 2,
    "tangent": 2,
    "validate": 2,
    "differentiated": 2,
    "divided": 2,
    "identical": 2,
    "twin": 2,
    "experiment": 2,
    "griewank": 2,
    "walther": 2,
    "binomial": 2,
    "checkpointing": 2,
    "consumption": 2,
    "specific": 2,
    "differentiate": 2,
    "iterative": 2,
    "come": 2,
    "implicit": 2,
    "stepping": 2,
    "scheme": 2,
    "checker": 2,
    "large": 2,
    "library": 2,
    "fact": 2,
    "report": 2,
    "able": 2,
    "reach": 2,
    "insufficient": 2,
    "perfectly": 2,
    "correctness": 2,
    "define": 2,
    "canonical": 2,
    "piecewise": 2,
    "defined": 2,
    "wider": 2,
    "better": 2,
    "previous": 2,
    "testing": 2,
    "common": 2,
    "offering": 2,
    "since": 2,
    "incorrect": 2,
    "describe": 2,
    "power": 2,
    "locally": 2,
    "preconditioned": 2,
    "scientific": 2,
    "scalable": 2,
    "partial": 2,
    "national": 2,
    "laboratory": 2,
    "lobpcg": 2,
    "symmetric": 2,
    "multigrid": 2,
    "numerically": 2,
    "correctly": 2,
    "rounding": 2,
    "flow": 2,
    "matter": 2,
    "bit": 2,
    "full": 2,
    "multicore": 2,
    "continue": 2,
    "gain": 2,
    "ground": 2,
    "algebra": 2,
    "reformulated": 2,
    "architectural": 2,
    "fine": 2,
    "grain": 2,
    "introduces": 2,
    "necessity": 2,
    "loose": 2,
    "synchronization": 2,
    "cholesky": 2,
    "lu": 2,
    "qr": 2,
    "represented": 2,
    "sequence": 2,
    "operate": 2,
    "dynamically": 2,
    "scheduled": 2,
    "resource": 2,
    "completely": 2,
    "hide": 2,
    "intrinsically": 2,
    "sequential": 2,
    "presented": 2,
    "lapack": 2,
    "exploited": 2,
    "blas": 2,
    "vendor": 2,
    "certify": 1,
    "mathematical": 1,
    "involve": 1,
    "exact": 1,
    "generates": 1,
    "theorem": 1,
    "treated": 1,
    "checked": 1,
    "logic": 1,
    "either": 1,
    "hol": 1,
    "light": 1,
    "companion": 1,
    "dealing": 1,
    "division": 1,
    "root": 1,
    "dyadic": 1,
    "fraction": 1,
    "endpoint": 1,
    "forward": 1,
    "necessary": 1,
    "asked": 1,
    "best": 1,
    "context": 1,
    "quickly": 1,
    "coarse": 1,
    "identify": 1,
    "seamlessly": 1,
    "additional": 1,
    "expressed": 1,
    "rule": 1,
    "intricate": 1,
    "showed": 1,
    "suited": 1,
    "piece": 1,
    "obligation": 1,
    "designer": 1,
    "produced": 1,
    "overloading": 1,
    "profiling": 1,
    "belonging": 1,
    "heterogeneous": 1,
    "sense": 1,
    "differ": 1,
    "brings": 1,
    "unified": 1,
    "view": 1,
    "composite": 1,
    "compatible": 1,
    "command": 1,
    "specified": 1,
    "script": 1,
    "going": 1,
    "perl": 1,
    "basic": 1,
    "statistical": 1,
    "change": 1,
    "emergence": 1,
    "simplicity": 1,
    "dictated": 1,
    "intricacy": 1,
    "epoch": 1,
    "turn": 1,
    "uniquely": 1,
    "quick": 1,
    "suggested": 1,
    "improves": 1,
    "reliability": 1,
    "graphical": 1,
    "bring": 1,
    "modification": 1,
    "performance": 1,
    "illustrated": 1,
    "varied": 1,
    "evaluation": 1,
    "extension": 1,
    "base": 1,
    "xolvers": 1,
    "publicly": 1,
    "released": 1,
    "serial": 1,
    "external": 1,
    "portable": 1,
    "extensible": 1,
    "toolkit": 1,
    "purpose": 1,
    "suite": 1,
    "argonne": 1,
    "built": 1,
    "lawrence": 1,
    "livermore": 1,
    "release": 1,
    "conjugate": 1,
    "gradient": 1,
    "advanced": 1,
    "efficiently": 1,
    "facilitates": 1,
    "integration": 1,
    "independently": 1,
    "strict": 1,
    "attention": 1,
    "component": 1,
    "interoperability": 1,
    "easy": 1,
    "compile": 1,
    "via": 1,
    "demonstrate": 1,
    "scalability": 1,
    "shared": 1,
    "including": 1,
    "beowulf": 1,
    "sun": 1,
    "fire": 1,
    "amd": 1,
    "opteron": 1,
    "workstation": 1,
    "ibm": 1,
    "supercomputer": 1,
    "preconditioning": 1,
    "approximation": 1,
    "laplacian": 1,
    "introduce": 1,
    "accurately": 1,
    "positive": 1,
    "integer": 1,
    "assuming": 1,
    "fused": 1,
    "fma": 1,
    "instruction": 1,
    "always": 1,
    "produce": 1,
    "discus": 1,
    "round": 1,
    "single": 1,
    "industrial": 1,
    "translated": 1,
    "nonlinear": 1,
    "ordinary": 1,
    "geometrical": 1,
    "shape": 1,
    "ode": 1,
    "resolved": 1,
    "simulation": 1,
    "hardware": 1,
    "architecture": 1,
    "native": 1,
    "multithreads": 1,
    "simulating": 1,
    "vast": 1,
    "awareness": 1,
    "machine": 1,
    "essential": 1,
    "allied": 1,
    "truncation": 1,
    "error": 1,
    "induce": 1,
    "interpretation": 1,
    "answer": 1,
    "kind": 1,
    "arbitrary": 1,
    "physic": 1,
    "big": 1,
    "extra": 1,
    "allocation": 1,
    "mean": 1,
    "introducing": 1,
    "overwriting": 1,
    "classical": 1,
    "overwritten": 1,
    "slightly": 1,
    "leading": 1,
    "exhaustive": 1,
    "search": 1,
    "pebble": 1,
    "game": 1,
    "massive": 1,
    "loop": 1,
    "element": 1,
    "wilson": 1,
    "heavy": 1,
    "flavor": 1,
    "production": 1,
    "deeply": 1,
    "inelastic": 1,
    "scattering": 1,
    "lead": 1,
    "infinite": 1,
    "harmonic": 1,
    "mellin": 1,
    "summation": 1,
    "sigma": 1,
    "discusses": 1,
    "generate": 1,
    "random": 1,
    "extensively": 1,
    "distance": 1,
    "generated": 1,
    "cause": 1,
    "lawson": 1,
    "hanson": 1,
    "proposes": 1,
    "acceptable": 1,
    "procedure": 1,
    "unless": 1,
    "done": 1,
    "internally": 1,
    "seems": 1,
    "much": 1,
    "rarer": 1,
    "expect": 1,
    "returned": 1,
    "incurs": 1,
    "added": 1,
    "overhead": 1,
    "hard": 1,
    "cody": 1,
    "waite": 1,
    "reasonably": 1,
    "grows": 1,
    "left": 1,
    "approximate": 1,
    "enough": 1,
    "mild": 1,
    "assumption": 1,
    "computed": 1,
    "working": 1,
    "step": 1,
    "significand": 1,
    "even": 1,
    "worst": 1,
    "recall": 1
}