{
    "robot": 183,
    "paper": 58,
    "environment": 50,
    "emotion": 42,
    "manipulator": 42,
    "proposed": 38,
    "show": 35,
    "eye": 28,
    "machining": 27,
    "problem": 26,
    "path": 26,
    "change": 25,
    "mobile": 25,
    "parallel": 25,
    "part": 23,
    "control": 23,
    "simple": 22,
    "design": 22,
    "network": 22,
    "modeling": 21,
    "present": 21,
    "simulation": 21,
    "state": 21,
    "analysis": 21,
    "stiffness": 20,
    "work": 19,
    "several": 19,
    "graph": 19,
    "tool": 19,
    "number": 18,
    "application": 18,
    "class": 18,
    "machine": 18,
    "computational": 17,
    "better": 17,
    "speed": 17,
    "local": 17,
    "platform": 17,
    "new": 17,
    "service": 17,
    "aim": 16,
    "set": 16,
    "high": 16,
    "rrt": 16,
    "initial": 16,
    "first": 16,
    "optimal": 16,
    "fatigue": 16,
    "byzantine": 16,
    "computing": 15,
    "value": 15,
    "human": 15,
    "motion": 15,
    "controller": 15,
    "stl": 15,
    "sufficient": 15,
    "sensor": 15,
    "teleoperation": 15,
    "distributed": 15,
    "joint": 15,
    "condition": 15,
    "actuator": 15,
    "field": 14,
    "expression": 14,
    "combination": 14,
    "necessary": 14,
    "object": 14,
    "convergence": 14,
    "focus": 13,
    "task": 13,
    "interface": 13,
    "navigation": 13,
    "presented": 13,
    "posture": 13,
    "policy": 13,
    "agent": 13,
    "trajectory": 13,
    "hsm": 13,
    "robotic": 12,
    "understanding": 12,
    "eligibility": 12,
    "displayed": 12,
    "importance": 12,
    "certainty": 12,
    "main": 12,
    "basic": 12,
    "idiotypic": 12,
    "solve": 12,
    "consider": 12,
    "asynchronous": 12,
    "leg": 12,
    "effect": 11,
    "coordinate": 11,
    "terminal": 11,
    "phase": 11,
    "moving": 11,
    "able": 11,
    "view": 11,
    "matrix": 11,
    "axial": 11,
    "software": 11,
    "parameter": 11,
    "move": 11,
    "assembly": 11,
    "vehicle": 11,
    "force": 11,
    "visual": 11,
    "consists": 10,
    "shown": 10,
    "influence": 10,
    "novel": 10,
    "context": 10,
    "behavior": 10,
    "variant": 10,
    "well": 10,
    "oblivious": 10,
    "bound": 10,
    "point": 10,
    "arbitrary": 10,
    "operation": 10,
    "given": 10,
    "virtual": 10,
    "list": 10,
    "demand": 10,
    "location": 10,
    "convex": 10,
    "propose": 10,
    "position": 10,
    "test": 10,
    "affective": 9,
    "factor": 9,
    "emotional": 9,
    "experience": 9,
    "content": 9,
    "conventional": 9,
    "mechanism": 9,
    "propagation": 9,
    "communicate": 9,
    "intent": 9,
    "according": 9,
    "mascot": 9,
    "humatronics": 9,
    "length": 9,
    "ltl": 9,
    "solving": 9,
    "real": 9,
    "solution": 9,
    "identical": 9,
    "interaction": 9,
    "configuration": 9,
    "robotics": 9,
    "reality": 9,
    "manual": 9,
    "physical": 9,
    "link": 9,
    "deal": 9,
    "fully": 9,
    "numerical": 9,
    "target": 9,
    "need": 8,
    "achieve": 8,
    "calculated": 8,
    "experimental": 8,
    "assumption": 8,
    "complex": 8,
    "rrts": 8,
    "particular": 8,
    "extension": 8,
    "probabilistic": 8,
    "known": 8,
    "coprime": 8,
    "cyclic": 8,
    "map": 8,
    "line": 8,
    "existing": 8,
    "muscle": 8,
    "case": 8,
    "detailed": 8,
    "al": 8,
    "within": 8,
    "constant": 8,
    "region": 8,
    "workspace": 8,
    "describe": 8,
    "orthoglide": 8,
    "deterministic": 8,
    "singularity": 8,
    "kinematic": 8,
    "critical": 7,
    "like": 7,
    "impact": 7,
    "good": 7,
    "idea": 7,
    "exploration": 7,
    "faster": 7,
    "experiment": 7,
    "degree": 7,
    "web": 7,
    "underlying": 7,
    "chain": 7,
    "tested": 7,
    "behaviour": 7,
    "without": 7,
    "random": 7,
    "evolutionary": 7,
    "evolve": 7,
    "symmetry": 7,
    "contrast": 7,
    "unknown": 7,
    "shape": 7,
    "required": 7,
    "however": 7,
    "many": 7,
    "job": 7,
    "load": 7,
    "computation": 7,
    "surface": 7,
    "lower": 7,
    "velocity": 7,
    "measure": 7,
    "correct": 7,
    "employ": 7,
    "example": 7,
    "kinematics": 7,
    "requires": 7,
    "distance": 7,
    "setting": 7,
    "vision": 7,
    "wall": 7,
    "area": 7,
    "large": 6,
    "understand": 6,
    "topic": 6,
    "aspect": 6,
    "episode": 6,
    "evidence": 6,
    "manipulation": 6,
    "called": 6,
    "hopping": 6,
    "time": 6,
    "communicated": 6,
    "together": 6,
    "additional": 6,
    "represented": 6,
    "fuzzy": 6,
    "corresponds": 6,
    "communication": 6,
    "easy": 6,
    "home": 6,
    "society": 6,
    "along": 6,
    "level": 6,
    "creation": 6,
    "available": 6,
    "shared": 6,
    "world": 6,
    "principle": 6,
    "lead": 6,
    "connected": 6,
    "capable": 6,
    "discussed": 6,
    "combined": 6,
    "ai": 6,
    "seeded": 6,
    "tree": 6,
    "efficient": 6,
    "even": 6,
    "though": 6,
    "informed": 6,
    "response": 6,
    "team": 6,
    "previous": 6,
    "anonymous": 6,
    "size": 6,
    "dimension": 6,
    "spherical": 6,
    "atom": 6,
    "ho": 6,
    "architecture": 6,
    "collaborative": 6,
    "composed": 6,
    "goal": 6,
    "important": 6,
    "msd": 6,
    "handling": 6,
    "evaluation": 6,
    "procedure": 6,
    "original": 6,
    "prioritized": 6,
    "quality": 6,
    "arrival": 6,
    "second": 6,
    "power": 6,
    "accuracy": 6,
    "family": 6,
    "additionally": 6,
    "oxygen": 6,
    "account": 6,
    "deadline": 6,
    "die": 6,
    "protocol": 6,
    "researcher": 5,
    "widely": 5,
    "face": 5,
    "major": 5,
    "recognizing": 5,
    "primary": 5,
    "issue": 5,
    "failure": 5,
    "improve": 5,
    "project": 5,
    "memory": 5,
    "possible": 5,
    "per": 5,
    "another": 5,
    "best": 5,
    "dimensional": 5,
    "combining": 5,
    "obstacle": 5,
    "assumed": 5,
    "scenario": 5,
    "ring": 5,
    "geometric": 5,
    "open": 5,
    "concept": 5,
    "movement": 5,
    "fixed": 5,
    "help": 5,
    "especially": 5,
    "risk": 5,
    "order": 5,
    "efficiency": 5,
    "plasmodium": 5,
    "technical": 5,
    "reference": 5,
    "patient": 5,
    "multiple": 5,
    "must": 5,
    "fraction": 5,
    "rate": 5,
    "adaptive": 5,
    "development": 5,
    "strategy": 5,
    "compliant": 5,
    "equation": 5,
    "allows": 5,
    "confirmed": 5,
    "translational": 5,
    "inverse": 5,
    "acceleration": 5,
    "characterization": 5,
    "difficult": 5,
    "global": 5,
    "planner": 5,
    "planning": 5,
    "obtain": 5,
    "choice": 5,
    "methodology": 5,
    "element": 5,
    "may": 5,
    "calibration": 5,
    "standard": 5,
    "multidisciplinary": 4,
    "direction": 4,
    "way": 4,
    "core": 4,
    "modeled": 4,
    "author": 4,
    "ability": 4,
    "transition": 4,
    "relationship": 4,
    "embodied": 4,
    "social": 4,
    "embedded": 4,
    "restriction": 4,
    "maximizing": 4,
    "predictive": 4,
    "loop": 4,
    "higher": 4,
    "rapid": 4,
    "form": 4,
    "sampling": 4,
    "become": 4,
    "popular": 4,
    "replanning": 4,
    "infrequent": 4,
    "address": 4,
    "greedy": 4,
    "static": 4,
    "sense": 4,
    "yet": 4,
    "unable": 4,
    "constrained": 4,
    "weak": 4,
    "yield": 4,
    "solved": 4,
    "initiate": 4,
    "unoriented": 4,
    "removing": 4,
    "positive": 4,
    "constructive": 4,
    "discus": 4,
    "certain": 4,
    "nearly": 4,
    "leading": 4,
    "formation": 4,
    "axialgen": 4,
    "prototype": 4,
    "generating": 4,
    "visibility": 4,
    "bucket": 4,
    "competitiveness": 4,
    "defined": 4,
    "upper": 4,
    "give": 4,
    "theoretical": 4,
    "introduced": 4,
    "community": 4,
    "arm": 4,
    "transform": 4,
    "theta": 4,
    "although": 4,
    "unit": 4,
    "complete": 4,
    "appropriate": 4,
    "easier": 4,
    "impossible": 4,
    "update": 4,
    "suitable": 4,
    "avoid": 4,
    "employed": 4,
    "productivity": 4,
    "modelling": 4,
    "planar": 4,
    "unique": 4,
    "output": 4,
    "designed": 4,
    "serve": 4,
    "citable": 4,
    "expected": 4,
    "associated": 4,
    "participant": 4,
    "considered": 4,
    "autonomous": 4,
    "ii": 4,
    "medical": 4,
    "evolution": 4,
    "specific": 4,
    "spring": 4,
    "involves": 4,
    "determine": 4,
    "wrist": 4,
    "image": 4,
    "interpolation": 4,
    "agreement": 4,
    "range": 4,
    "synchrony": 4,
    "prove": 4,
    "despite": 4,
    "subset": 4,
    "various": 4,
    "tolerates": 4,
    "synchronous": 4,
    "corda": 4,
    "established": 4,
    "optimum": 4,
    "produce": 4,
    "grammar": 4,
    "embedding": 4,
    "maximum": 4,
    "relevant": 4,
    "saccade": 4,
    "low": 4,
    "combine": 4,
    "proposes": 4,
    "iso": 4,
    "elastic": 4,
    "proven": 3,
    "viable": 3,
    "comprised": 3,
    "published": 3,
    "majority": 3,
    "causal": 3,
    "rendered": 3,
    "smaller": 3,
    "concerned": 3,
    "formal": 3,
    "cognitive": 3,
    "appraisal": 3,
    "theory": 3,
    "emergent": 3,
    "motivation": 3,
    "computer": 3,
    "others": 3,
    "expressing": 3,
    "neglected": 3,
    "barrett": 3,
    "mesquita": 3,
    "ochsner": 3,
    "gross": 3,
    "look": 3,
    "call": 3,
    "effort": 3,
    "launch": 3,
    "journal": 3,
    "synthetic": 3,
    "motivate": 3,
    "initiative": 3,
    "measurable": 3,
    "psychology": 3,
    "investigate": 3,
    "psychological": 3,
    "already": 3,
    "addressing": 3,
    "speeding": 3,
    "applicable": 3,
    "running": 3,
    "turning": 3,
    "backwards": 3,
    "event": 3,
    "balancing": 3,
    "preprint": 3,
    "withdrawn": 3,
    "revision": 3,
    "trace": 3,
    "propagates": 3,
    "temporal": 3,
    "predecessor": 3,
    "biped": 3,
    "crawling": 3,
    "confirm": 3,
    "accelerates": 3,
    "household": 3,
    "being": 3,
    "friendly": 3,
    "fashion": 3,
    "convey": 3,
    "activeness": 3,
    "viewpoint": 3,
    "conveying": 3,
    "liveliness": 3,
    "understood": 3,
    "capability": 3,
    "exploit": 3,
    "rule": 3,
    "controlled": 3,
    "segment": 3,
    "reason": 3,
    "derive": 3,
    "diverse": 3,
    "transferred": 3,
    "immune": 3,
    "said": 3,
    "handdesigned": 3,
    "addition": 3,
    "turned": 3,
    "substantial": 3,
    "option": 3,
    "merges": 3,
    "structurally": 3,
    "compromising": 3,
    "transferability": 3,
    "subject": 3,
    "continuous": 3,
    "perfect": 3,
    "kind": 3,
    "plus": 3,
    "type": 3,
    "among": 3,
    "limiting": 3,
    "averaging": 3,
    "longest": 3,
    "representing": 3,
    "individual": 3,
    "space": 3,
    "accessible": 3,
    "key": 3,
    "ax": 3,
    "whose": 3,
    "positioning": 3,
    "modify": 3,
    "augmented": 3,
    "operator": 3,
    "cooperative": 3,
    "teleassistance": 3,
    "augmentation": 3,
    "interact": 3,
    "safer": 3,
    "remote": 3,
    "networked": 3,
    "mixed": 3,
    "vr": 3,
    "distant": 3,
    "permit": 3,
    "heterogeneous": 3,
    "musculoskeletal": 3,
    "disorder": 3,
    "assessment": 3,
    "index": 3,
    "working": 3,
    "validated": 3,
    "integrated": 3,
    "manufacturing": 3,
    "industry": 3,
    "still": 3,
    "described": 3,
    "property": 3,
    "input": 3,
    "laboratory": 3,
    "report": 3,
    "lab": 3,
    "involving": 3,
    "assistive": 3,
    "delay": 3,
    "thus": 3,
    "independent": 3,
    "operate": 3,
    "bounded": 3,
    "general": 3,
    "previously": 3,
    "therefore": 3,
    "partitioning": 3,
    "introduces": 3,
    "component": 3,
    "directly": 3,
    "equitable": 3,
    "subregions": 3,
    "achieving": 3,
    "actuating": 3,
    "localized": 3,
    "compliance": 3,
    "including": 3,
    "offer": 3,
    "displacement": 3,
    "mean": 3,
    "cad": 3,
    "motor": 3,
    "function": 3,
    "phi": 3,
    "generate": 3,
    "past": 3,
    "industrial": 3,
    "limit": 3,
    "cartesian": 3,
    "via": 3,
    "approximate": 3,
    "specification": 3,
    "detail": 3,
    "exhibit": 3,
    "hand": 3,
    "evolved": 3,
    "fov": 3,
    "generation": 3,
    "criterion": 3,
    "embed": 3,
    "essentially": 3,
    "notion": 3,
    "difficulty": 3,
    "becomes": 3,
    "accordingly": 3,
    "whenever": 3,
    "competition": 3,
    "integrate": 3,
    "pft": 3,
    "conformal": 3,
    "integrates": 3,
    "following": 3,
    "forward": 3,
    "drive": 3,
    "collision": 3,
    "edge": 3,
    "jacobian": 3,
    "simplified": 3,
    "axis": 3,
    "identification": 3,
    "offset": 3,
    "parallelism": 3,
    "measuring": 3,
    "deviation": 3,
    "today": 3,
    "geometrical": 3,
    "feed": 3,
    "technology": 3,
    "circular": 3,
    "chablat": 3,
    "series": 3,
    "supporting": 2,
    "sustainable": 2,
    "meaningful": 2,
    "dialogue": 2,
    "publish": 2,
    "facebook": 2,
    "hypothesis": 2,
    "gradually": 2,
    "pool": 2,
    "episodic": 2,
    "know": 2,
    "encounter": 2,
    "friend": 2,
    "presenting": 2,
    "see": 2,
    "achieves": 2,
    "novelty": 2,
    "derived": 2,
    "sensorimotor": 2,
    "varying": 2,
    "individually": 2,
    "wheel": 2,
    "coordinated": 2,
    "physically": 2,
    "overall": 2,
    "longer": 2,
    "less": 2,
    "outperform": 2,
    "shorter": 2,
    "interpretation": 2,
    "tackle": 2,
    "fix": 2,
    "unfeasible": 2,
    "stuck": 2,
    "subsequently": 2,
    "restart": 2,
    "document": 2,
    "thesis": 2,
    "unpredictable": 2,
    "traversing": 2,
    "holonomic": 2,
    "kinodynamic": 2,
    "unpredictably": 2,
    "availability": 2,
    "rapidly": 2,
    "exploring": 2,
    "explored": 2,
    "overcome": 2,
    "shortcoming": 2,
    "interesting": 2,
    "pursuit": 2,
    "gathering": 2,
    "break": 2,
    "circulants": 2,
    "rather": 2,
    "circulant": 2,
    "automatically": 2,
    "least": 2,
    "linearly": 2,
    "stretched": 2,
    "urban": 2,
    "closed": 2,
    "building": 2,
    "street": 2,
    "block": 2,
    "guide": 2,
    "concentrate": 2,
    "explanation": 2,
    "illustration": 2,
    "definition": 2,
    "keywords": 2,
    "medial": 2,
    "isovists": 2,
    "coverage": 2,
    "asked": 2,
    "accomplish": 2,
    "learned": 2,
    "tactile": 2,
    "perspective": 2,
    "gabriely": 2,
    "rimon": 2,
    "every": 2,
    "online": 2,
    "arbitrarily": 2,
    "badly": 2,
    "assuming": 2,
    "clearance": 2,
    "optimally": 2,
    "competitive": 2,
    "crystalline": 2,
    "prototyped": 2,
    "consist": 2,
    "independently": 2,
    "manipulable": 2,
    "side": 2,
    "neighbor": 2,
    "suffice": 2,
    "reconfigure": 2,
    "sequential": 2,
    "reconfiguration": 2,
    "run": 2,
    "log": 2,
    "step": 2,
    "total": 2,
    "slightly": 2,
    "nlogn": 2,
    "theoretically": 2,
    "universally": 2,
    "reconfigurable": 2,
    "built": 2,
    "health": 2,
    "mechanical": 2,
    "subjective": 2,
    "place": 2,
    "mathematically": 2,
    "quickly": 2,
    "maintenance": 2,
    "msds": 2,
    "digital": 2,
    "potential": 2,
    "ergonomics": 2,
    "commercial": 2,
    "easily": 2,
    "special": 2,
    "cell": 2,
    "device": 2,
    "candidate": 2,
    "role": 2,
    "healthcare": 2,
    "georgia": 2,
    "tech": 2,
    "released": 2,
    "website": 2,
    "september": 2,
    "publication": 2,
    "resulted": 2,
    "amyotrophic": 2,
    "lateral": 2,
    "sclerosis": 2,
    "targeted": 2,
    "interview": 2,
    "drawn": 2,
    "emory": 2,
    "center": 2,
    "ranked": 2,
    "retrieval": 2,
    "intend": 2,
    "inform": 2,
    "benchmarking": 2,
    "arrive": 2,
    "characteristic": 2,
    "travel": 2,
    "group": 2,
    "rely": 2,
    "robust": 2,
    "limited": 2,
    "provably": 2,
    "follows": 2,
    "finally": 2,
    "chapter": 2,
    "describes": 2,
    "term": 2,
    "future": 2,
    "workload": 2,
    "subregion": 2,
    "partition": 2,
    "overconstrained": 2,
    "flexible": 2,
    "multidimensional": 2,
    "flexibility": 2,
    "coupling": 2,
    "kinetostatic": 2,
    "unloaded": 2,
    "singular": 2,
    "advantage": 2,
    "recursive": 2,
    "connecting": 2,
    "located": 2,
    "knowing": 2,
    "iterative": 2,
    "prismatic": 2,
    "dynamic": 2,
    "latter": 2,
    "selection": 2,
    "gammar": 2,
    "remains": 2,
    "characterized": 2,
    "correcting": 2,
    "sample": 2,
    "identify": 2,
    "close": 2,
    "soft": 2,
    "establish": 2,
    "build": 2,
    "obtained": 2,
    "jerk": 2,
    "carried": 2,
    "asymptotically": 2,
    "exact": 2,
    "beforehand": 2,
    "recall": 2,
    "allowed": 2,
    "instead": 2,
    "draw": 2,
    "connection": 2,
    "decide": 2,
    "apart": 2,
    "surprisingly": 2,
    "resilience": 2,
    "correctness": 2,
    "cautious": 2,
    "guarantee": 2,
    "always": 2,
    "inside": 2,
    "fault": 2,
    "match": 2,
    "tolerated": 2,
    "neural": 2,
    "discusses": 2,
    "observed": 2,
    "capillary": 2,
    "blood": 2,
    "reaching": 2,
    "near": 2,
    "klavins": 2,
    "et": 2,
    "program": 2,
    "rewriting": 2,
    "degano": 2,
    "montanari": 2,
    "year": 2,
    "ago": 2,
    "generalize": 2,
    "soloveichik": 2,
    "winfree": 2,
    "determinism": 2,
    "tile": 2,
    "partial": 2,
    "converse": 2,
    "processor": 2,
    "topologically": 2,
    "conclude": 2,
    "defining": 2,
    "hull": 2,
    "inhabited": 2,
    "conclusion": 2,
    "executing": 2,
    "subroutine": 2,
    "import": 2,
    "synchronizer": 2,
    "coin": 2,
    "flipping": 2,
    "successfully": 2,
    "walking": 2,
    "bipedal": 2,
    "encourage": 2,
    "population": 2,
    "around": 2,
    "demes": 2,
    "fitness": 2,
    "progressively": 2,
    "automation": 2,
    "modification": 2,
    "fpga": 2,
    "module": 2,
    "construct": 2,
    "mechanically": 2,
    "aid": 2,
    "prone": 2,
    "eventually": 2,
    "converge": 2,
    "apriori": 2,
    "exhibiting": 2,
    "contribution": 2,
    "twofold": 2,
    "solves": 2,
    "generic": 2,
    "constrasts": 2,
    "partially": 2,
    "moreover": 2,
    "since": 2,
    "fourier": 2,
    "camera": 2,
    "head": 2,
    "shift": 2,
    "logarithmic": 2,
    "translation": 2,
    "scene": 2,
    "include": 2,
    "corresponding": 2,
    "useful": 2,
    "pattern": 2,
    "chaos": 2,
    "away": 2,
    "periodic": 2,
    "bifurcation": 2,
    "slower": 2,
    "capture": 2,
    "small": 2,
    "objective": 2,
    "vibration": 2,
    "rigidity": 2,
    "elasticity": 2,
    "performance": 2,
    "base": 2,
    "rotated": 2,
    "replace": 2,
    "formulation": 2,
    "dedicated": 2,
    "requirement": 2,
    "demonstrated": 2,
    "kinematical": 2,
    "template": 2,
    "upon": 2,
    "description": 2,
    "needle": 2,
    "observation": 2,
    "respect": 2,
    "measured": 2,
    "estimate": 2,
    "treated": 2,
    "essential": 2,
    "validity": 2,
    "external": 2,
    "forging": 2,
    "cam": 2,
    "adequacy": 2,
    "preparation": 2,
    "constrains": 2,
    "inherent": 2,
    "lie": 2,
    "complementary": 2,
    "devoted": 2,
    "analysed": 2,
    "capacity": 2,
    "mould": 2,
    "decrease": 2,
    "analyse": 2,
    "insufficient": 2,
    "energy": 2,
    "electric": 2,
    "illustrative": 2,
    "vector": 2,
    "illustrated": 2,
    "recently": 2,
    "prediction": 2,
    "benefit": 2,
    "fidelity": 2,
    "impedance": 2,
    "believed": 1,
    "expose": 1,
    "meanwhile": 1,
    "inspector": 1,
    "disadvantage": 1,
    "workshop": 1,
    "defect": 1,
    "collection": 1,
    "consuming": 1,
    "ergonomic": 1,
    "closely": 1,
    "predict": 1,
    "objectively": 1,
    "automatic": 1,
    "lot": 1,
    "due": 1,
    "overload": 1,
    "cumulative": 1,
    "dhm": 1,
    "commercialized": 1,
    "exposure": 1,
    "recovery": 1,
    "extended": 1,
    "physarum": 1,
    "polycephalum": 1,
    "single": 1,
    "huge": 1,
    "visible": 1,
    "naked": 1,
    "myriad": 1,
    "nucleus": 1,
    "promising": 1,
    "substrate": 1,
    "shortest": 1,
    "proximity": 1,
    "tessellation": 1,
    "primitive": 1,
    "ideal": 1,
    "amorphous": 1,
    "biological": 1,
    "massive": 1,
    "processing": 1,
    "adhered": 1,
    "resting": 1,
    "water": 1,
    "propel": 1,
    "oscillating": 1,
    "protoplasmic": 1,
    "pseudopodium": 1,
    "phenomenology": 1,
    "controlling": 1,
    "propelled": 1,
    "board": 1,
    "randomly": 1,
    "require": 1,
    "amount": 1,
    "remain": 1,
    "completion": 1,
    "minimizes": 1,
    "achievable": 1,
    "heavy": 1,
    "spend": 1,
    "depends": 1,
    "coefficient": 1,
    "coordination": 1,
    "wait": 1,
    "repairman": 1,
    "centralized": 1,
    "assignment": 1,
    "applicability": 1,
    "operating": 1,
    "whereby": 1,
    "partitioned": 1,
    "spatially": 1,
    "scalable": 1,
    "stabilize": 1,
    "includes": 1,
    "physician": 1,
    "diagnostic": 1,
    "therapeutic": 1,
    "practice": 1,
    "intervention": 1,
    "paradigm": 1,
    "domain": 1,
    "trend": 1,
    "assisting": 1,
    "handicapped": 1,
    "person": 1,
    "rehabilitation": 1,
    "replacement": 1,
    "limb": 1,
    "organ": 1,
    "scope": 1,
    "sharing": 1,
    "equalize": 1,
    "assigned": 1,
    "divided": 1,
    "equal": 1,
    "bijective": 1,
    "correspondence": 1,
    "iii": 1,
    "responsible": 1,
    "request": 1,
    "originating": 1,
    "allow": 1,
    "regular": 1,
    "polygon": 1,
    "classic": 1,
    "lloyd": 1,
    "diagram": 1,
    "replaces": 1,
    "comparative": 1,
    "vertical": 1,
    "freedom": 1,
    "belongs": 1,
    "delta": 1,
    "agile": 1,
    "inertial": 1,
    "determined": 1,
    "emphasized": 1,
    "preliminary": 1,
    "torque": 1,
    "carry": 1,
    "closure": 1,
    "discrete": 1,
    "cone": 1,
    "full": 1,
    "entropy": 1,
    "simpler": 1,
    "solely": 1,
    "inequality": 1,
    "locate": 1,
    "distortion": 1,
    "misalignment": 1,
    "elegant": 1,
    "corrected": 1,
    "fitting": 1,
    "pass": 1,
    "sufficiently": 1,
    "intermediate": 1,
    "word": 1,
    "rectification": 1,
    "safety": 1,
    "comfort": 1,
    "ca": 1,
    "personnel": 1,
    "isolated": 1,
    "envelope": 1,
    "try": 1,
    "ensure": 1,
    "satisfied": 1,
    "presence": 1,
    "cubic": 1,
    "homogeneous": 1,
    "quaternion": 1,
    "mitsubishi": 1,
    "behind": 1,
    "infrared": 1,
    "light": 1,
    "explore": 1,
    "recorded": 1,
    "lesser": 1,
    "navigate": 1,
    "microscopic": 1,
    "nanorobots": 1,
    "oxidize": 1,
    "bloodstream": 1,
    "glucose": 1,
    "aggregated": 1,
    "circumferential": 1,
    "release": 1,
    "passing": 1,
    "red": 1,
    "micron": 1,
    "picowatts": 1,
    "plasma": 1,
    "pump": 1,
    "tank": 1,
    "onboard": 1,
    "storage": 1,
    "collect": 1,
    "support": 1,
    "burst": 1,
    "magnitude": 1,
    "larger": 1,
    "depletion": 1,
    "heating": 1,
    "surrounding": 1,
    "tissue": 1,
    "entirely": 1,
    "ambient": 1,
    "affecting": 1,
    "nanomedicine": 1,
    "treatment": 1,
    "facilitate": 1,
    "enhancement": 1,
    "projected": 1,
    "conception": 1,
    "prototyping": 1,
    "distributing": 1,
    "action": 1,
    "growing": 1,
    "proposal": 1,
    "oriented": 1,
    "reprogrammable": 1,
    "logic": 1,
    "detect": 1,
    "wireless": 1,
    "transmission": 1,
    "interfaced": 1,
    "semantic": 1,
    "excellent": 1,
    "opportunity": 1,
    "umbrella": 1,
    "inspiring": 1,
    "collaboration": 1,
    "interplay": 1,
    "ignored": 1,
    "venue": 1,
    "outline": 1,
    "participation": 1,
    "binocular": 1,
    "projective": 1,
    "numerically": 1,
    "cortex": 1,
    "saccadic": 1,
    "eyeball": 1,
    "incisive": 1,
    "stable": 1,
    "percept": 1,
    "constancy": 1,
    "maintained": 1,
    "neuronal": 1,
    "receptive": 1,
    "retinotopically": 1,
    "organized": 1,
    "cortical": 1,
    "prior": 1,
    "onset": 1,
    "giving": 1,
    "brain": 1,
    "access": 1,
    "acquisition": 1,
    "across": 1,
    "computable": 1,
    "fft": 1,
    "retinotopy": 1,
    "retinotopic": 1,
    "remaps": 1,
    "presaccadic": 1,
    "postsaccadic": 1,
    "frame": 1,
    "perisaccadic": 1,
    "mislocalization": 1,
    "abstract": 1,
    "harmonic": 1,
    "neuroscience": 1,
    "background": 1,
    "material": 1,
    "elucidate": 1,
    "interwove": 1,
    "primate": 1,
    "physiological": 1,
    "fact": 1,
    "emphasize": 1,
    "uniquely": 1,
    "natural": 1,
    "examine": 1,
    "braitenberg": 1,
    "chaotic": 1,
    "steve": 1,
    "mesburger": 1,
    "alfred": 1,
    "hubler": 1,
    "facing": 1,
    "turn": 1,
    "right": 1,
    "left": 1,
    "far": 1,
    "flat": 1,
    "stay": 1,
    "regardless": 1,
    "represents": 1,
    "narrow": 1,
    "square": 1,
    "triangle": 1,
    "sawtooth": 1,
    "wave": 1,
    "border": 1,
    "period": 1,
    "doubling": 1,
    "reported": 1,
    "separately": 1,
    "introduce": 1,
    "seek": 1,
    "guard": 1,
    "boundary": 1,
    "dynamically": 1,
    "arriving": 1,
    "rectangle": 1,
    "continuously": 1,
    "opposite": 1,
    "towards": 1,
    "maximize": 1,
    "captured": 1,
    "directed": 1,
    "acyclic": 1,
    "suggest": 1,
    "regime": 1,
    "servicing": 1,
    "minimum": 1,
    "hamiltonian": 1,
    "swim": 1,
    "eel": 1,
    "swimming": 1,
    "realization": 1,
    "vertebra": 1,
    "skin": 1,
    "fin": 1,
    "reach": 1,
    "formed": 1,
    "framework": 1,
    "french": 1,
    "utility": 1,
    "optimised": 1,
    "negligible": 1,
    "needed": 1,
    "long": 1,
    "submitted": 1,
    "bending": 1,
    "twisting": 1,
    "deformation": 1,
    "preferable": 1,
    "poorer": 1,
    "analytic": 1,
    "congruent": 1,
    "deg": 1,
    "reduced": 1,
    "quadratic": 1,
    "sequence": 1,
    "plotted": 1,
    "cup": 1,
    "play": 1,
    "improvement": 1,
    "precision": 1,
    "analytical": 1,
    "describing": 1,
    "statistical": 1,
    "error": 1,
    "confidence": 1,
    "interval": 1,
    "grid": 1,
    "transforms": 1,
    "prescribed": 1,
    "transformation": 1,
    "satisfy": 1,
    "modern": 1,
    "brachytherapy": 1,
    "brief": 1,
    "review": 1,
    "inclining": 1,
    "insertion": 1,
    "prostate": 1,
    "mounted": 1,
    "stepper": 1,
    "accommodates": 1,
    "seed": 1,
    "dispenser": 1,
    "mick": 1,
    "applicator": 1,
    "preserve": 1,
    "nominal": 1,
    "identified": 1,
    "sensitivity": 1,
    "measurement": 1,
    "adapted": 1,
    "integrating": 1,
    "technological": 1,
    "accessibility": 1,
    "assist": 1,
    "assistant": 1,
    "improving": 1,
    "analysing": 1,
    "consequently": 1,
    "basis": 1,
    "ultimately": 1,
    "bore": 1,
    "nowadays": 1,
    "maker": 1,
    "invested": 1,
    "shaped": 1,
    "choose": 1,
    "functional": 1,
    "economical": 1,
    "elaborate": 1,
    "production": 1,
    "induce": 1,
    "estimating": 1,
    "focused": 1,
    "calculation": 1,
    "esprit": 1,
    "visualised": 1,
    "arc": 1,
    "nature": 1,
    "discontinuity": 1,
    "encountered": 1,
    "visualisation": 1,
    "engineer": 1,
    "validate": 1,
    "decompose": 1,
    "dy": 1,
    "finishing": 1,
    "extraction": 1,
    "resource": 1,
    "expert": 1,
    "knowledge": 1,
    "outstanding": 1,
    "aeronautics": 1,
    "automotive": 1,
    "done": 1,
    "purchasing": 1,
    "wide": 1,
    "situation": 1,
    "pose": 1,
    "judicious": 1,
    "meeting": 1,
    "expressed": 1,
    "insofar": 1,
    "customer": 1,
    "manufacturer": 1,
    "quantitatively": 1,
    "qualitatively": 1,
    "direct": 1,
    "recommended": 1,
    "presentation": 1,
    "relation": 1,
    "concurrent": 1,
    "arranged": 1,
    "orientation": 1,
    "normal": 1,
    "plane": 1,
    "perpendicular": 1,
    "placement": 1,
    "consumption": 1,
    "minimal": 1,
    "pkm": 1,
    "geometrically": 1,
    "actuation": 1,
    "moment": 1,
    "dependency": 1,
    "ucker": 1,
    "finite": 1,
    "infinity": 1,
    "constituting": 1,
    "row": 1,
    "formulated": 1,
    "algebra": 1,
    "choosing": 1,
    "depending": 1,
    "free": 1,
    "exist": 1,
    "feasible": 1,
    "define": 1,
    "maximal": 1,
    "execute": 1,
    "twodifferent": 1,
    "tracked": 1,
    "construction": 1,
    "achieved": 1,
    "enrichment": 1,
    "octree": 1,
    "structure": 1,
    "greater": 1,
    "interest": 1,
    "comparator": 1,
    "indicator": 1,
    "attached": 1,
    "universal": 1,
    "magnetic": 1,
    "stand": 1,
    "sequentially": 1,
    "tcp": 1,
    "inappropriate": 1,
    "might": 1,
    "occupational": 1,
    "biomechanics": 1,
    "optimize": 1,
    "stage": 1,
    "minimizing": 1,
    "stress": 1,
    "enough": 1,
    "optimisation": 1,
    "moo": 1,
    "predicting": 1,
    "drilling": 1,
    "european": 1,
    "aeronautic": 1,
    "company": 1,
    "eads": 1,
    "acting": 1,
    "end": 1,
    "separated": 1,
    "rigid": 1,
    "valid": 1,
    "mode": 1,
    "implicitly": 1,
    "assumes": 1,
    "loading": 1,
    "amendment": 1,
    "equilibrium": 1,
    "reaction": 1,
    "designer": 1,
    "buckling": 1,
    "beam": 1,
    "linearization": 1,
    "inversion": 1,
    "active": 1,
    "passive": 1,
    "unconstrained": 1,
    "friction": 1,
    "bandwidth": 1,
    "go": 1,
    "common": 1,
    "principal": 1,
    "stiffer": 1,
    "placed": 1,
    "gear": 1,
    "driven": 1,
    "intentionally": 1,
    "reduce": 1,
    "deflection": 1,
    "accurately": 1,
    "hooke": 1,
    "law": 1,
    "servo": 1,
    "desired": 1,
    "shock": 1,
    "tolerance": 1,
    "desirable": 1,
    "legged": 1,
    "exoskeleton": 1,
    "amplification": 1,
    "haptic": 1,
    "suspension": 1,
    "variation": 1,
    "hydraulic": 1
}